odoo/addons/l10n_br_stock_account_report/README.rst
odoo/addons/l10n_br_stock_account_report/__init__.py
odoo/addons/l10n_br_stock_account_report/__manifest__.py
odoo/addons/l10n_br_stock_account_report/i18n/l10n_br_stock_account_report.pot
odoo/addons/l10n_br_stock_account_report/i18n/pt_BR.po
odoo/addons/l10n_br_stock_account_report/readme/CONFIGURE.md
odoo/addons/l10n_br_stock_account_report/readme/CONTRIBUTORS.md
odoo/addons/l10n_br_stock_account_report/readme/CREDITS.md
odoo/addons/l10n_br_stock_account_report/readme/DESCRIPTION.md
odoo/addons/l10n_br_stock_account_report/readme/HISTORY.md
odoo/addons/l10n_br_stock_account_report/readme/INSTALL.md
odoo/addons/l10n_br_stock_account_report/readme/ROADMAP.md
odoo/addons/l10n_br_stock_account_report/readme/USAGE.md
odoo/addons/l10n_br_stock_account_report/report/l10n_br_p7_model_inventory_report.xml
odoo/addons/l10n_br_stock_account_report/report/l10n_br_p7_model_inventory_report_view.xml
odoo/addons/l10n_br_stock_account_report/security/ir.model.access.csv
odoo/addons/l10n_br_stock_account_report/static/description/icon.png
odoo/addons/l10n_br_stock_account_report/static/description/index.html
odoo/addons/l10n_br_stock_account_report/tests/__init__.py
odoo/addons/l10n_br_stock_account_report/tests/test_l10n_br_p7_model_inventory_report.py
odoo/addons/l10n_br_stock_account_report/wizards/__init__.py
odoo/addons/l10n_br_stock_account_report/wizards/l10n_br_p7_model_inventory_report_wizard.py
odoo/addons/l10n_br_stock_account_report/wizards/l10n_br_p7_model_inventory_report_wizard_view.xml
odoo_addon_l10n_br_stock_account_report-16.0.2.1.0.dist-info/METADATA
odoo_addon_l10n_br_stock_account_report-16.0.2.1.0.dist-info/WHEEL
odoo_addon_l10n_br_stock_account_report-16.0.2.1.0.dist-info/top_level.txt
odoo_addon_l10n_br_stock_account_report-16.0.2.1.0.dist-info/RECORD
